AutoStatLib/AutoStatLib.py
AutoStatLib/StatPlots.py
AutoStatLib/__init__.py
AutoStatLib/__main__.py
AutoStatLib/_version.py
AutoStatLib/helpers.py
AutoStatLib/normality_tests.py
AutoStatLib/statistical_tests.py
AutoStatLib/text_formatting.py
autostatlib-0.2.24.dist-info/licenses/LICENSE
autostatlib-0.2.24.dist-info/METADATA
autostatlib-0.2.24.dist-info/WHEEL
autostatlib-0.2.24.dist-info/top_level.txt
autostatlib-0.2.24.dist-info/RECORD
