Metadata-Version: 2.4
Name: AutoStatLib
Version: 0.2.24
Summary: AutoStatLib - a simple statistical analysis tool
Author: Stemonitis, SciWare LLC
Author-email: konung-yaropolk <yaropolk1995@gmail.com>
License-Expression: LGPL-2.1-or-later
Project-URL: Homepage, https://github.com/konung-yaropolk/AutoStatLib
Project-URL: Repository, https://github.com/konung-yaropolk/AutoStatLib.git
Project-URL: Issues, https://github.com/konung-yaropolk/AutoStatLib/issues
Keywords: Science,Statistics
Classifier: Programming Language :: Python
Classifier: Programming Language :: Python :: 3
Classifier: Programming Language :: Python :: 3.10
Classifier: Operating System :: OS Independent
Classifier: Development Status :: 4 - Beta
Classifier: Intended Audience :: Developers
Classifier: Intended Audience :: Science/Research
Classifier: Natural Language :: English
Classifier: Topic :: Software Development :: Libraries
Classifier: Topic :: Software Development :: Libraries :: Python Modules
Classifier: Topic :: Scientific/Engineering
Classifier: Topic :: Scientific/Engineering :: Information Analysis
Requires-Python: >=3.10
License-File: LICENSE
Requires-Dist: numpy
Requires-Dist: scipy
Requires-Dist: statsmodels
Requires-Dist: matplotlib
Requires-Dist: seaborn
Requires-Dist: scikit-posthocs
Requires-Dist: pandas
Dynamic: license-file
